
[

{"name": "Spider Man", "phone": "6789876543", "comics": "Marvel", "image":"spider.jpg"},
{"name": "Bat Man", "phone": "1234567890", "comics": "DC", "image":"batman.jpeg"},
{"name": "Iron Man", "phone": "7654321985", "comics": "Marvel", "image":"ironman.jpg"},
{"name": "Super Man", "phone": "9876543210", "comics": "DC", "image":"superman.jpg"},
{"name": "DeadPool", "phone": "9085674321", "comics": "Marvel", "image":"deedpol.jpg"},
{"name": "Wolverine", "phone": "9098675435", "comics": "Marvel", "image":"wolv.jpg"}

]
